setup.py
installib/__init__.py
installib/compare.py
installib/obfuscation_checker.py
installib/test.py
installib/windows.py
installib.egg-info/PKG-INFO
installib.egg-info/SOURCES.txt
installib.egg-info/dependency_links.txt
installib.egg-info/not-zip-safe
installib.egg-info/requires.txt
installib.egg-info/top_level.txt
installib/behave_steps/__init__.py
installib/behave_steps/steps.py