Metadata-Version: 1.1
Name: installib
Version: 0.6
Summary: Install helper library
Home-page: https://github.com/ivanprjcts/installib
Author: Ivan Martin
Author-email: ivanprjcts@gmail.com
License: BSD
Platform: UNKNOWN
Classifier: Intended Audience :: Developers
Classifier: License :: OSI Approved :: BSD License
Classifier: Operating System :: OS Independent
Classifier: Programming Language :: Python
Classifier: Programming Language :: Python :: 2.7
